PhonemeSER.py
Train_test.py
predict.py
FormantsLib/FormantsExtract.py
FormantsLib/FormatsHDFread.py
examples/example.py
examples/predict.py
PhonemeSER-1.0.3.dist-info/LICENSE.md
PhonemeSER-1.0.3.dist-info/METADATA
PhonemeSER-1.0.3.dist-info/WHEEL
PhonemeSER-1.0.3.dist-info/top_level.txt
PhonemeSER-1.0.3.dist-info/RECORD
