Metadata-Version: 2.1
Name: PhonemeSER
Version: 1.0.3
Summary: Predict speech emotions from wav files.
Home-page: https://github.com/tabahi/Phoneme-Converge-SER
Author: Tabahi - Abdul Rehman
Author-email: tabahi@hotmail.fr
License: UNKNOWN
Platform: UNKNOWN
Classifier: Programming Language :: Python :: 3
Classifier: License :: OSI Approved :: MIT License
Classifier: Operating System :: OS Independent
Requires-Python: >=3.6
License-File: LICENSE.md
Requires-Dist: sklearn
Requires-Dist: pydub
Requires-Dist: wavio
